[
    {
        "Nom" : "Maillot Clarity - Edition 2021",
        "Prix" : 39,
        "Face" : "images/equipe/Maillot_face.png",
        "Bleu" : "images/equipe/Maillot_bleu.png",
        "Dos" : "images/equipe/Maillot_dos.pnd",
        "Violet" : "images/equipe/Maillot_violet.png",
        "Description1" : "Impression haute qualité",
        "Description2" : "Double col",
        "Description3" : "100% Polyester de haute qualité",
        "Description4" : "100% Fabriqué en France",
        "Taille1" : "XS",
        "Taille2" : "S",
        "Taille3" : "M",
        "Taille4" : "L",
        "Taille5" : "XL",
        "Quantité1" : 0,
        "Quantité2" : 0,
        "Quantité3" : 0,
        "Quantité4" : 0,
        "Quantité5" : 0
    },
    {
        "Nom" : "Masque Clarity",
        "Prix" : 9.00,
        "Face" : "images/equipe/Masque_face.png",
        "Bleu" : "images/equipe/Masque_bleu.png",
        "Violet" : "images/equipe/Masque_violet.png",
        "Description1" : "Non destiné à un usage médical",
        "Description2" : "Lavable",
        "Description3" : "100% Polyester de haute qualité",
        "Description4" : "100% Fabriqué en France",
        "Taille1" : "Enfant",
        "Taille2" : "Adulte",
        "Quantité1" : 0,
        "Quantité2" : 0
    },
    {
        "Nom" : "Manchette Clarity",
        "Prix" : 19.00,
        "Extérieur" : "images/equipe/bras_ext.png",
        "Intérieur" : "images/equipe/bras_int.png",
        "Description1" : "Réduction des frictions",
        "Description2" : "Meilleure circulation sanguine",
        "Description3" : "75% Polyester de haute qualité + 25% Élasthanne",
        "Description4" : "100% Fabriqué en France",
        "Taille1" : "XS",
        "Taille2" : "S",
        "Taille3" : "M",
        "Taille4" : "L",
        "Taille5" : "XL",
        "Quantité1" : 0,
        "Quantité2" : 0,
        "Quantité3" : 0,
        "Quantité4" : 0,
        "Quantité5" : 0
    }
]